cli/main.py
dataengx/__init__.py
dataengx/converters.py
dataengx-0.1.0.dist-info/METADATA
dataengx-0.1.0.dist-info/WHEEL
dataengx-0.1.0.dist-info/entry_points.txt
dataengx-0.1.0.dist-info/top_level.txt
dataengx-0.1.0.dist-info/RECORD
