Metadata-Version: 2.4
Name: dataengx
Version: 0.1.0
Summary: Data engineering utilities for converting and querying data files
Author-email: Samuel Mana-ay <manaaysamuel@gmail.com>
Classifier: Programming Language :: Python :: 3
Classifier: Operating System :: OS Independent
Requires-Python: >=3.7
Requires-Dist: pandas
Requires-Dist: duckdb
Requires-Dist: pyarrow
